vignore/__init__.py
vignore/cli.py
vignore-1.0.8.dist-info/licenses/LICENSE
vignore-1.0.8.dist-info/METADATA
vignore-1.0.8.dist-info/WHEEL
vignore-1.0.8.dist-info/entry_points.txt
vignore-1.0.8.dist-info/top_level.txt
vignore-1.0.8.dist-info/RECORD
