Metadata-Version: 2.4
Name: vignore
Version: 1.0.8
Summary: Visualize ignored files and directories by rules.
Home-page: https://github.com/james4ever0/vignore
License-File: LICENSE
Requires-Dist: numpy
Requires-Dist: rich
Requires-Dist: textual
Requires-Dist: jinja2
Requires-Dist: beartype
Requires-Dist: aiofiles
Requires-Dist: asyncio
Requires-Dist: humanize
Dynamic: description
Dynamic: description-content-type
Dynamic: home-page
Dynamic: license-file
Dynamic: requires-dist
Dynamic: summary
